vsscli/SystemStatus.py
vsscli/VssCLI.py
vsscli/__init__.py
vsscli/cli.py
vsscli/emoji.py
vsscli/utils.py
vsscli-0.5.1.data/scripts/vss_bash_completer
vsscli-0.5.1.dist-info/LICENSE.txt
vsscli-0.5.1.dist-info/METADATA
vsscli-0.5.1.dist-info/WHEEL
vsscli-0.5.1.dist-info/entry_points.txt
vsscli-0.5.1.dist-info/top_level.txt
vsscli-0.5.1.dist-info/RECORD
