Metadata-Version: 2.1
Name: vsscli
Version: 0.5.1
Summary: ITS Private Cloud Command Line Interface
Home-page: https://eis.utoronto.ca/~vss/vsscli/
Author: University of Toronto - ITS
Author-email: jm.lopez@utoronto.ca
Maintainer: Virtualization & Storage Services
Maintainer-email: vss-py@eis.utoronto.ca
License: MIT License
Download-URL: https://gitlab-ee.eis.utoronto.ca/vss/vsscli/tags
Platform: Windows
Platform: Linux
Platform: Solaris
Platform: Mac OS-X
Platform: Unix
Platform: OpenBSD
Classifier: Development Status :: 5 - Production/Stable
Classifier: Intended Audience :: Developers
Classifier: Intended Audience :: System Administrators
Classifier: Natural Language :: English
Classifier: License :: OSI Approved :: MIT License
Classifier: Programming Language :: Python
Classifier: Programming Language :: Python :: 2.7
Classifier: Programming Language :: Python :: 3.5
Classifier: Programming Language :: Python :: 3.6
Classifier: Programming Language :: Python :: 3.7
Requires-Dist: click (==6.7)
Requires-Dist: pyvss (>=0.9.26)
Requires-Dist: tabulate (==0.8.1)
Requires-Dist: Pygments (==2.2.0)
Requires-Dist: python-dateutil (==2.7.3)
Requires-Dist: prompt-toolkit (==1.0.15)
Requires-Dist: click-repl (==0.1.5)
